aiextraction/Extract_with_OpenAi.py
aiextraction/Extract_with_Pixtral.py
aiextraction/__init__.py
aiextraction-1.0.3.dist-info/METADATA
aiextraction-1.0.3.dist-info/WHEEL
aiextraction-1.0.3.dist-info/top_level.txt
aiextraction-1.0.3.dist-info/RECORD
