Metadata-Version: 2.1
Name: aiextraction
Version: 1.0.3
Summary: A library for text extraction from images into json files using OpenAI and Pixtral
Author: John Petris
Requires-Dist: annotated-types>=0.7.0
Requires-Dist: anyio>=4.6.0
Requires-Dist: certifi>=2024.8.30
Requires-Dist: charset-normalizer>=3.3.2
Requires-Dist: colorama>=0.4.6
Requires-Dist: distro>=1.9.0
Requires-Dist: docutils>=0.21.2
Requires-Dist: eval-type-backport>=0.2.0
Requires-Dist: h11>=0.14.0
Requires-Dist: httpcore>=1.0.5
Requires-Dist: httpx>=0.27.2
Requires-Dist: idna>=3.10
Requires-Dist: importlib-metadata>=8.5.0
Requires-Dist: jaraco.classes>=3.4.0
Requires-Dist: jaraco.context>=6.0.1
Requires-Dist: jaraco.functools>=4.0.2
Requires-Dist: jiter>=0.5.0
Requires-Dist: jsonpath-python>=1.0.6
Requires-Dist: keyring>=25.4.1
Requires-Dist: markdown-it-py>=3.0.0
Requires-Dist: mdurl>=0.1.2
Requires-Dist: mistralai>=1.1.0
Requires-Dist: more-itertools>=10.5.0
Requires-Dist: mypy-extensions>=1.0.0
Requires-Dist: nh3>=0.2.18
Requires-Dist: openai>=1.47.1
Requires-Dist: pkginfo>=1.10.0
Requires-Dist: pydantic>=2.9.2
Requires-Dist: pydantic-core>=2.23.4
Requires-Dist: Pygments>=2.18.0
Requires-Dist: python-dateutil>=2.8.2
Requires-Dist: pywin32-ctypes>=0.2.3
Requires-Dist: readme-renderer>=44.0
Requires-Dist: requests>=2.32.3
Requires-Dist: requests-toolbelt>=1.0.0
Requires-Dist: rfc3986>=2.0.0
Requires-Dist: rich>=13.8.1
Requires-Dist: setuptools>=75.1.0
Requires-Dist: six>=1.16.0
Requires-Dist: sniffio>=1.3.1
Requires-Dist: tqdm>=4.66.5
Requires-Dist: twine>=5.1.1
Requires-Dist: typing-inspect>=0.9.0
Requires-Dist: typing-extensions>=4.12.2
Requires-Dist: urllib3>=2.2.3
Requires-Dist: wheel>=0.44.0
Requires-Dist: zipp>=3.20.2
